{"id":"d5827beff9efad845e664ae43a04a73b","type":"flow","start":1774348198300,"name":"ebookChapterFlow","status":0}
{"id":"d5827beff9efad845e664ae43a04a73b","type":"flow","start":1774348198300,"name":"ebookChapterFlow","end":1774348198608.2139,"status":2}
{"id":"626efc9b231ec6f94947fc1059181866","type":"flow","start":1774348198726,"name":"ebookChapterFlow","status":0}
{"id":"626efc9b231ec6f94947fc1059181866","type":"flow","start":1774348198726,"name":"ebookChapterFlow","end":1774348198823.279,"status":2}
